auto_retrieval_plugin/.env
auto_retrieval_plugin/.well-known/ai-plugin.json
auto_retrieval_plugin/.well-known/default-ai-plugin.json
auto_retrieval_plugin/.well-known/logo.png
auto_retrieval_plugin/.well-known/openapi.yaml
auto_retrieval_plugin/__init__.py
auto_retrieval_plugin/config.yml
auto_retrieval_plugin/datastore/__init__.py
auto_retrieval_plugin/datastore/datastore.py
auto_retrieval_plugin/datastore/executor/Dockerfile
auto_retrieval_plugin/datastore/executor/__init__.py
auto_retrieval_plugin/datastore/executor/config.yml
auto_retrieval_plugin/datastore/executor/docarray_v1.py
auto_retrieval_plugin/datastore/factory.py
auto_retrieval_plugin/flow.yml
auto_retrieval_plugin/gateway.py
auto_retrieval_plugin/models/__init__.py
auto_retrieval_plugin/models/api.py
auto_retrieval_plugin/models/models.py
auto_retrieval_plugin/retrieval_plugin.py
auto_retrieval_plugin/scripts/__init__.py
auto_retrieval_plugin/scripts/process_json/README.md
auto_retrieval_plugin/scripts/process_json/__init__.py
auto_retrieval_plugin/scripts/process_json/example.json
auto_retrieval_plugin/scripts/process_json/process_json.py
auto_retrieval_plugin/scripts/process_jsonl/README.md
auto_retrieval_plugin/scripts/process_jsonl/__init__.py
auto_retrieval_plugin/scripts/process_jsonl/example.jsonl
auto_retrieval_plugin/scripts/process_jsonl/process_jsonl.py
auto_retrieval_plugin/scripts/process_zip/README.md
auto_retrieval_plugin/scripts/process_zip/__init__.py
auto_retrieval_plugin/scripts/process_zip/example.zip
auto_retrieval_plugin/scripts/process_zip/process_zip.py
auto_retrieval_plugin/services/__init__.py
auto_retrieval_plugin/services/chunks.py
auto_retrieval_plugin/services/date.py
auto_retrieval_plugin/services/extract_metadata.py
auto_retrieval_plugin/services/file.py
auto_retrieval_plugin/services/openai.py
auto_retrieval_plugin/services/pii_detection.py
auto_retrieval_plugin-0.1.5.dist-info/LICENSE
auto_retrieval_plugin-0.1.5.dist-info/METADATA
auto_retrieval_plugin-0.1.5.dist-info/WHEEL
auto_retrieval_plugin-0.1.5.dist-info/entry_points.txt
auto_retrieval_plugin-0.1.5.dist-info/RECORD
